allennlp/__init__.py
allennlp/__main__.py
allennlp/py.typed
allennlp/version.py
allennlp/commands/__init__.py
allennlp/commands/_checklist_internal.py
allennlp/commands/build_vocab.py
allennlp/commands/cached_path.py
allennlp/commands/checklist.py
allennlp/commands/count_instances.py
allennlp/commands/diff.py
allennlp/commands/evaluate.py
allennlp/commands/find_learning_rate.py
allennlp/commands/predict.py
allennlp/commands/print_results.py
allennlp/commands/push_to_hf.py
allennlp/commands/subcommand.py
allennlp/commands/test_install.py
allennlp/commands/train.py
allennlp/common/__init__.py
allennlp/common/cached_transformers.py
allennlp/common/checks.py
allennlp/common/file_utils.py
allennlp/common/from_params.py
allennlp/common/lazy.py
allennlp/common/logging.py
allennlp/common/meta.py
allennlp/common/model_card.py
allennlp/common/params.py
allennlp/common/plugins.py
allennlp/common/push_to_hf.py
allennlp/common/registrable.py
allennlp/common/sequences.py
allennlp/common/task_card.py
allennlp/common/tqdm.py
allennlp/common/util.py
allennlp/common/testing/__init__.py
allennlp/common/testing/checklist_test.py
allennlp/common/testing/confidence_check_test.py
allennlp/common/testing/distributed_test.py
allennlp/common/testing/interpret_test.py
allennlp/common/testing/model_test_case.py
allennlp/common/testing/test_case.py
allennlp/confidence_checks/__init__.py
allennlp/confidence_checks/normalization_bias_verification.py
allennlp/confidence_checks/verification_base.py
allennlp/confidence_checks/task_checklists/__init__.py
allennlp/confidence_checks/task_checklists/question_answering_suite.py
allennlp/confidence_checks/task_checklists/sentiment_analysis_suite.py
allennlp/confidence_checks/task_checklists/task_suite.py
allennlp/confidence_checks/task_checklists/textual_entailment_suite.py
allennlp/confidence_checks/task_checklists/utils.py
allennlp/data/__init__.py
allennlp/data/batch.py
allennlp/data/image_loader.py
allennlp/data/instance.py
allennlp-2.10.1.dist-info/LICENSE
allennlp-2.10.1.dist-info/METADATA
allennlp-2.10.1.dist-info/WHEEL
allennlp-2.10.1.dist-info/entry_points.txt
allennlp-2.10.1.dist-info/top_level.txt
allennlp-2.10.1.dist-info/RECORD
