Metadata-Version: 2.1
Name: allennlp
Version: 2.10.1
Summary: An open-source NLP research library, built on PyTorch.
Home-page: https://github.com/allenai/allennlp
Author: Allen Institute for Artificial Intelligence
Author-email: allennlp@allenai.org
License: Apache
Keywords: allennlp NLP deep learning machine reading
Classifier: Intended Audience :: Science/Research
Classifier: Development Status :: 3 - Alpha
Classifier: License :: OSI Approved :: Apache Software License
Classifier: Programming Language :: Python :: 3
Classifier: Topic :: Scientific/Engineering :: Artificial Intelligence
Requires-Python: >=3.7.1
Provides-Extra: checklist
Provides-Extra: all
Provides-Extra: dev
License-File: LICENSE
